README.rst
setup.py
django_furl/__init__.py
django_furl.egg-info/PKG-INFO
django_furl.egg-info/SOURCES.txt
django_furl.egg-info/dependency_links.txt
django_furl.egg-info/top_level.txt
django_furl/templatetags/__init__.py
django_furl/templatetags/furl_tags.py