Metadata-Version: 1.1
Name: django-furl
Version: 0.0.3
Summary: A simple Django extension for url manipulation
Home-page: https://github.com/poxip/django-furl
Author: Michal Proszek
Author-email: michal.proszek@gmail.com
License: MIT
Keywords: django url manipulation furl
Platform: UNKNOWN
Classifier: Environment :: Web Environment
Classifier: Framework :: Django
Classifier: Intended Audience :: Developers
Classifier: License :: OSI Approved :: MIT License
Classifier: Operating System :: OS Independent
Classifier: Programming Language :: Python
Classifier: Programming Language :: Python :: 3
Classifier: Programming Language :: Python :: 3.4
Classifier: Programming Language :: Python :: 3.5
Classifier: Topic :: Internet :: WWW/HTTP
Classifier: Topic :: Internet :: WWW/HTTP :: Dynamic Content
